hagadias/__init__.py
hagadias/assets/IBMGRAPH.TXT
hagadias/assets/SourceCodePro-Bold.ttf
hagadias/assets/SourceCodePro-Semibold.ttf
hagadias/character_codes.py
hagadias/constants.py
hagadias/dicebag.py
hagadias/gameroot.py
hagadias/helpers.py
hagadias/qudobject.py
hagadias/qudobject_props.py
hagadias/qudpopulation.py
hagadias/qudtile.py
hagadias/svalue.py
hagadias/tileanimator.py
hagadias/tileanimator_creategif.py
hagadias/tilepainter.py
hagadias/tilestyle.py
hagadias-1.2.1.dist-info/LICENSE
hagadias-1.2.1.dist-info/WHEEL
hagadias-1.2.1.dist-info/METADATA
hagadias-1.2.1.dist-info/RECORD
