Metadata-Version: 2.1
Name: hagadias
Version: 1.2.1
Summary: Extract game data from the Caves of Qud roguelike
Home-page: https://github.com/TrashMonks/hagadias
License: AGPL-3.0
Keywords: Caves,Qud
Author: syntaxaire
Author-email: syntaxaire@gmail.com
Maintainer: syntaxaire
Maintainer-email: syntaxaire@gmail.com
Requires-Python: >=3.10,<4.0
Classifier: License :: OSI Approved :: GNU Affero General Public License v3
Classifier: Programming Language :: Python :: 3
Classifier: Programming Language :: Python :: 3.10
Requires-Dist: Pillow (>=9.2.0,<10.0.0)
Requires-Dist: anytree (>=2.8.0,<3.0.0)
Requires-Dist: lxml (>=4.9.1,<5.0.0)
Requires-Dist: pefile (>=2022.5.30,<2023.0.0)
Project-URL: Repository, https://github.com/TrashMonks/hagadias
